Metadata-Version: 1.2
Name: acgv1signer
Version: 1.1
Summary: BaiduCloud-V1-auth
Home-page: https://github.com/Galvin-wjw/ACG-Samples/blob/master/acgv1signer/acgv1signer.py
Author: galvinwang
Author-email: 137606834@qq.com
Maintainer: galvinwang
Maintainer-email: 137606834@qq.com
License: BSD License
Platform: all
Classifier: Development Status :: 4 - Beta
Classifier: Operating System :: OS Independent
Classifier: Intended Audience :: Developers
Classifier: License :: OSI Approved :: BSD License
Classifier: Programming Language :: Python
Classifier: Programming Language :: Python :: Implementation
Classifier: Programming Language :: Python :: 3
Classifier: Programming Language :: Python :: 3.4
Classifier: Programming Language :: Python :: 3.5
Classifier: Programming Language :: Python :: 3.6
Classifier: Programming Language :: Python :: 3.7
Classifier: Topic :: Software Development :: Libraries
